container/__init__.py
container/container.py
container/errors.py
container/main.py
magic_container-0.0.4.dist-info/LICENSE
magic_container-0.0.4.dist-info/METADATA
magic_container-0.0.4.dist-info/WHEEL
magic_container-0.0.4.dist-info/top_level.txt
magic_container-0.0.4.dist-info/RECORD
