Metadata-Version: 2.1
Name: magic-container
Version: 0.0.4
Summary: Thread-safe, magical and persistent dict for Python.
Home-page: https://github.com/KingKevin23/container
Author: KingKevin23
Author-email: code@kingkevin.de
License: UNKNOWN
Project-URL: Bug Tracker, https://github.com/KingKevin23/container/issues
Platform: UNKNOWN
Classifier: Programming Language :: Python :: 3
Classifier: License :: OSI Approved :: MIT License
Classifier: Operating System :: OS Independent
Requires-Python: >=3.8
License-File: LICENSE
Requires-Dist: sqlitedict (>=1.7.0)
